README.txt
setup.py
markfiltration/__init__.py
markfiltration/markfiltration.py
pytest_markfiltration.egg-info/PKG-INFO
pytest_markfiltration.egg-info/SOURCES.txt
pytest_markfiltration.egg-info/dependency_links.txt
pytest_markfiltration.egg-info/entry_points.txt
pytest_markfiltration.egg-info/requires.txt
pytest_markfiltration.egg-info/top_level.txt