Metadata-Version: 1.0
Name: pytest-markfiltration
Version: 0.7
Summary: UNKNOWN
Home-page: https://github.com/adamgoucher/pytest-markfiltration
Author: adam goucher
Author-email: adam@element34.ca
License: UNKNOWN
Platform: UNKNOWN
Classifier: Development Status :: 3 - Alpha
Classifier: Intended Audience :: Developers
Classifier: License :: OSI Approved :: GNU General Public License (GPL)
Classifier: Operating System :: POSIX
Classifier: Operating System :: Microsoft :: Windows
Classifier: Operating System :: MacOS :: MacOS X
Classifier: Topic :: Software Development :: Testing
Classifier: Topic :: Software Development :: Quality Assurance
Classifier: Topic :: Utilities
Classifier: Programming Language :: Python
